[
  {
    "id": "5 L.172015-81/24-38",
    "exam": "81/24",
    "num": "38",
    "text": "D’acord amb la Llei 15/2017, de 21 de juliol, d’igualtat efectiva de dones i homes, què s’entén per equitat de gènere?",
    "options": {
      "a": "la situació que garanteix la presència de les dones en una proporció adequada en cada circumstància.",
      "b": "la distribució justa de drets, els beneficis, les obligacions, les oportunitats i els recursos sobre la base del reconeixement i el respecte de la diferència de dones i homes en la societat.",
      "c": "l’acció educadora que potencia la igualtat real d’oportunitats i valora indistintament l’experiència, les aptituds i l’aportació social i cultural de dones i homes, en igualtat de drets.",
      "d": "la situació que garanteix una presència de dones i homes segons la qual cap sexe no supera el 60% del conjunt de persones. 14 16 17 18 19 20 21 22"
    },
    "answer": "b"
  },
  {
    "id": "5 L.172015-81/23-100",
    "exam": "81/23",
    "num": "100",
    "text": "La Llei 17/2015, del 21 de juliol, d’igualtat efectiva de dones i homes, té per objecte:",
    "options": {
      "a": "fer efectiu el dret a la discriminació per raó de sexe en l’àmbit laboral.",
      "b": "garantir l’equitat de gènere exclusivament en l’àmbit de la salut.",
      "c": "establir i regular els mecanismes i recursos per a fer efectiu el dret a la igualtat i a la no- discriminació per raó de sexe en tots els àmbits, etapes i circumstàncies de la vida.",
      "d": "la prevenció per la reducció de la incidència de la problemàtica de la violència masclista per tal de reduir els factors de risc en l'etapa de l'adolescència. 28 30"
    },
    "answer": "c"
  },
  {
    "id": "5 L.172015-81/21-94",
    "exam": "81/21",
    "num": "94",
    "text": "Quina llei regula la igualtat de gènere home-dona? (Pla d'igualtat).",
    "options": {
      "a": "el decret legislatiu 1/1997, de 31 d'octubre.",
      "b": "la llei 5/1994, de 4 de maig.",
      "c": "la llei 17/2015, de 21 de juliol.",
      "d": "la llei 10/1994, d'11 de juliol."
    },
    "answer": "c"
  }
]